{"0": "affirm", "1": "apple_tree_issue", "2": "ask_crop_recommendation", "3": "bot_challenge", "4": "common_potato_diseases", "5": "cover_crop_options", "6": "crops_for_acidic_soil", "7": "crops_for_alkaline_soil", "8": "crops_for_clayey_soil", "9": "crops_for_cool_moist_climate", "10": "crops_for_hot_dry_climate", "11": "crops_for_partial_shade", "12": "crops_for_sandy_soil", "13": "cucumber_pest", "14": "deny", "15": "drip_irrigation_benefits", "16": "goodbye", "17": "grapevine_disease", "18": "greet", "19": "harvest_time_wheat", "20": "ideal_strawberry_pH", "21": "identify_nutrient_deficiencies", "22": "improve_soil_fertility", "23": "mood_great", "24": "mood_unhappy", "25": "pepper_fruit_issue", "26": "pollinator_attracting_crops", "27": "potato_planting_depth", "28": "potato_spacing", "29": "prevent_pests", "30": "space_saving_crops", "31": "sustainable_farming_practices", "32": "tomato_leaf_issue", "33": "water_amount_tomato_plants", "34": "watering_frequency_potatoes", "35": "weather", "36": "wheat_disease"}